[
  {
    "room_no": 1,
    "bed_sharing": "SINGLE",
    "person1_name": "jalu",
    "floor_no": 1,
    "person1_id": 1
  },
  {
    "room_no": 2,
    "bed_sharing": "DOUBLE",
    "person1_name": "jani",
    "person2_name": "jalu",
    "floor_no": 1,
    "person1_id": 2,
    "person2_id": 1
  },
  {
    "room_no": 3,
    "bed_sharing": "SINGLE",
    "person1_name": "kannan",
    "floor_no": 1,
    "person1_id": 3
  },
  {
    "room_no": 4,
    "bed_sharing": "DOUBLE",
    "person1_name": "yoga",
    "person2_name": "kannan",
    "floor_no": 2,
    "person1_id": 4,
    "person2_id": 3
  }
]